[
  {
    "title": "Los Sims 4 Creciendo en Familia Pack de Expansión",
    "image": "https://media.game.es/COVERV2/3D_L/214/214517.png",
    "price": "29 '99 € "
  },
  {
    "title": "Los Sims 4: Años High School Pack de Expansión CIAB",
    "image": "https://media.game.es/COVERV2/3D_L/206/206303.png",
    "price": "19 '99 € "
  },
  {
    "title": "Los Sims 4: Ambiente Acogedor",
    "image": "https://media.game.es/COVERV2/3D_L/208/208725.png",
    "price": "9 '99 € "
  },
  {
    "title": "Los Sims 4 + Los Sims 4 Star Wars viaje a Batuu",
    "image": "https://media.game.es/COVERV2/3D_L/182/182598.png",
    "price": "24 '99 € "
  },
  {
    "title": "Los Sims 4 Vida Ecologica",
    "image": "https://media.game.es/COVERV2/3D_L/180/180225.png",
    "price": "19 '99 € "
  },
  {
    "title": "Los Sims 4: Escapada en la Nieve",
    "image": "https://media.game.es/COVERV2/3D_L/184/184262.png",
    "price": "19 '99 € "
  },
  {
    "title": "Los Sims 4 Dias de Universidad",
    "image": "https://media.game.es/COVERV2/3D_L/174/174821.png",
    "price": "19 '99 € "
  },
  {
    "title": "Los Sims 4 Vida Isleña",
    "image": "https://media.game.es/COVERV2/3D_L/167/167551.png",
    "price": "19 '99 € "
  },
  {
    "title": "Los Sims 4 Rumbo A La Fama",
    "image": "https://media.game.es/COVERV2/3D_L/158/158215.png",
    "price": "19 '99 € "
  },
  {
    "title": "Los Sims 3 [D]",
    "image": "https://media.game.es/COVERV2/3D_L/087/087348.png",
    "price": "14 '95 € "
  },
  {
    "title": "Los Sims 4 y Las Cuatro Estaciones",
    "image": "https://media.game.es/COVERV2/3D_L/151/151313.png",
    "price": "19 '99 € "
  },
  {
    "title": "Los Sims 4",
    "image": "https://media.game.es/COVERV2/3D_L/140/140473.png",
    "price": "9 '99 € "
  },
  {
    "title": "Los Sims 4 + Los Sims 4 Vida Isleña",
    "image": "https://media.game.es/COVERV2/3D_L/168/168449.png",
    "price": "44 '95 € "
  },
  {
    "title": "Los Sims 4 + Perros y Gatos",
    "image": "https://media.game.es/COVERV2/3D_L/143/143443.png",
    "price": "49 '99 € "
  },
  {
    "title": "Los Sims 4 + Rumbo A La Fama Colección",
    "image": "https://media.game.es/COVERV2/3D_L/158/158216.png",
    "price": "49 '99 € "
  },
  {
    "title": "Los Sims 4 Urbanitas",
    "image": "https://media.game.es/COVERV2/3D_L/132/132263.png",
    "price": "19 '99 € "
  },
  {
    "title": "Los Sims 4 ¿Quedamos?",
    "image": "https://media.game.es/COVERV2/3D_L/119/119989.png",
    "price": "19 '99 € "
  },
  {
    "title": "Los Sims 3",
    "image": "https://media.game.es/COVERV2/3D_L/074/074354.png",
    "price": "12 '95 € "
  },
  {
    "title": "Los Sims 4: ¡A Trabajar!",
    "image": "https://media.game.es/COVERV2/3D_L/112/112284.png",
    "price": "19 '99 € "
  },
  {
    "title": "The Sims 4: Spa Day Xbox One",
    "image": "https://media.game.es/COVERV2/3D_L/166/166016.png",
    "price": "19 '99 € "
  },
  {
    "title": "The Sims 4: Bowling Night Stuff Xbox One",
    "image": "https://media.game.es/COVERV2/3D_L/164/164407.png",
    "price": "9 '99 € "
  },
  {
    "title": "The Sims 4: City Living Xbox One",
    "image": "https://media.game.es/COVERV2/3D_L/145/145394.png",
    "price": "39 '99 € "
  },
  {
    "title": "Los Sims 4 Vida Ecologica (REACONDICIONADO)",
    "image": "https://media.game.es/COVERV2/3D_L/216/216824.png",
    "price": "15 '99 € "
  },
  {
    "title": "Los Sims 4 Vida Isleña (REACONDICIONADO)",
    "image": "https://media.game.es/COVERV2/3D_L/216/216825.png",
    "price": "15 '99 € "
  },
  {
    "title": "The Sims 4 - Cottage Living Xbox One",
    "image": "https://media.game.es/COVERV2/3D_L/203/203782.png",
    "price": "39 '99 € "
  },
  {
    "title": "The Sims™ 4: Paranormal Stuff Pack Xbox One - Plays On Xbox Series X|S",
    "image": "https://media.game.es/COVERV2/3D_L/203/203723.png",
    "price": "9 '99 € "
  },
  {
    "title": "The Sims 4: Snowy Escape Xbox One - Plays On Xbox Series X|S",
    "image": "https://media.game.es/COVERV2/3D_L/203/203688.png",
    "price": "39 '99 € "
  },
  {
    "title": "The Sims™ 4 Star Wars™: Journey To Batuu Xbox One - Plays On Xbox Series X|S",
    "image": "https://media.game.es/COVERV2/3D_L/203/203634.png",
    "price": "19 '99 € "
  },
  {
    "title": "The Sims 4: Nifty Knitting Xbox One",
    "image": "https://media.game.es/COVERV2/3D_L/203/203604.png",
    "price": "9 '99 € "
  },
  {
    "title": "The Sims 4: Eco-Lifestyle Xbox One",
    "image": "https://media.game.es/COVERV2/3D_L/203/203567.png",
    "price": "39 '99 € "
  },
  {
    "title": "The Sims 4: Cats And Dogs Plus My First Pet Stuff Xbox One",
    "image": "https://www.game.es/Content/img/no_disponible.png",
    "price": "39 '99 € "
  },
  {
    "title": "The Sims™ 4: Fun Outside Bundle Xbox One",
    "image": "https://media.game.es/COVERV2/3D_L/203/203549.png",
    "price": "49 '99 € "
  },
  {
    "title": "The Sims 4: Tiny Living Stuff Xbox One",
    "image": "https://media.game.es/COVERV2/3D_L/203/203532.png",
    "price": "9 '99 € "
  },
  {
    "title": "The Sims 4: Discovery University (Ep08) Xbox One",
    "image": "https://media.game.es/COVERV2/3D_L/177/177082.png",
    "price": "39 '99 € "
  },
  {
    "title": "Los Sims 4 + Dias de Universidad",
    "image": "https://media.game.es/COVERV2/3D_L/175/175149.png",
    "price": "59 '95 € "
  },
  {
    "title": "The Sims 4: Realm Of Magic Xbox One",
    "image": "https://media.game.es/COVERV2/3D_L/177/177089.png",
    "price": "19 '99 € "
  },
  {
    "title": "The Sims 4: Moschino Stuff Pack Xbox One",
    "image": "https://media.game.es/COVERV2/3D_L/177/177090.png",
    "price": "9 '99 € "
  },
  {
    "title": "The Sims 4: Island Living Xbox One",
    "image": "https://media.game.es/COVERV2/3D_L/203/203452.png",
    "price": "39 '99 € "
  },
  {
    "title": "The Sims 4: Strangerville Xbox One",
    "image": "https://media.game.es/COVERV2/3D_L/168/168522.png",
    "price": "19 '99 € "
  },
  {
    "title": "The Sims 4: Fitness Stuff Xbox One",
    "image": "https://media.game.es/COVERV2/3D_L/164/164408.png",
    "price": "9 '99 € "
  },
  {
    "title": "The Sims 4: Get Famous Xbox One",
    "image": "https://media.game.es/COVERV2/3D_L/162/162382.png",
    "price": "39 '99 € "
  },
  {
    "title": "The Sims 4: Movie Hangout Stuff Xbox One",
    "image": "https://media.game.es/COVERV2/3D_L/162/162374.png",
    "price": "9 '99 € "
  },
  {
    "title": "The Sims 4: Bundle (Seasons, Jungle Adventure, Spooky Stuff) Xbox One",
    "image": "https://media.game.es/COVERV2/3D_L/203/203380.png",
    "price": "49 '99 € "
  },
  {
    "title": "The Sims 4: Outdoor Retreat Xbox One",
    "image": "https://media.game.es/COVERV2/3D_L/160/160973.png",
    "price": "19 '99 € "
  },
  {
    "title": "The Sims 4: Jungle Adventure Xbox One",
    "image": "https://media.game.es/COVERV2/3D_L/160/160977.png",
    "price": "19 '99 € "
  },
  {
    "title": "The Sims 4: Seasons Xbox One",
    "image": "https://media.game.es/COVERV2/3D_L/160/160998.png",
    "price": "39 '99 € "
  },
  {
    "title": "The Sims 4: Bundle (Cats & Dogs, Parenthood, Toddler Stuff) Xbox One",
    "image": "https://media.game.es/COVERV2/3D_L/203/203144.png",
    "price": "49 '99 € "
  },
  {
    "title": "The Sims 4: Spooky Stuff Xbox One",
    "image": "https://media.game.es/COVERV2/3D_L/158/158445.png",
    "price": "9 '99 € "
  },
  {
    "title": "The Sims 4: Get Together Xbox One",
    "image": "https://media.game.es/COVERV2/3D_L/156/156552.png",
    "price": "39 '99 € "
  },
  {
    "title": "The Sims 4: Laundry Day Stuff Xbox One",
    "image": "https://media.game.es/COVERV2/3D_L/162/162340.png",
    "price": "9 '99 € "
  },
  {
    "title": "The Sims 4: Cats & Dogs Xbox One",
    "image": "https://media.game.es/COVERV2/3D_L/151/151505.png",
    "price": "39 '99 € "
  },
  {
    "title": "Pack Los Sims 4 + Las Cuatro Estaciones",
    "image": "https://media.game.es/COVERV2/3D_L/151/151314.png",
    "price": "49 '99 € "
  },
  {
    "title": "The Sims 4: Kids Room Stuff Xbox One",
    "image": "https://media.game.es/COVERV2/3D_L/151/151503.png",
    "price": "9 '99 € "
  },
  {
    "title": "The Sims 4: Parenthood Xbox One",
    "image": "https://media.game.es/COVERV2/3D_L/151/151504.png",
    "price": "19 '99 € "
  },
  {
    "title": "The Sims 4: Toddler Stuff Xbox One",
    "image": "https://media.game.es/COVERV2/3D_L/151/151502.png",
    "price": "9 '99 € "
  },
  {
    "title": "The Sims 4: Backyard Stuff Xbox One",
    "image": "https://media.game.es/COVERV2/3D_L/151/151501.png",
    "price": "9 '99 € "
  },
  {
    "title": "The Sims 4: Bundle (Get To Work, Dine Out, Cool Kitchen Stuff) Xbox One",
    "image": "https://media.game.es/COVERV2/3D_L/203/203076.png",
    "price": "49 '99 € "
  },
  {
    "title": "Los Sims 4 Colección 7",
    "image": "https://media.game.es/COVERV2/3D_L/147/147805.png",
    "price": "29 '95 € "
  },
  {
    "title": "The Sims 4: Cool Kitchen Stuff Xbox One",
    "image": "https://www.game.es/Content/img/no_disponible.png",
    "price": "9 '99 € "
  },
  {
    "title": "The Sims 4: Luxury Party Stuff Xbox One",
    "image": "https://media.game.es/COVERV2/3D_L/145/145387.png",
    "price": "9 '99 € "
  }
]
